crosscompute_image/__init__.py
crosscompute_image/type.jinja2
crosscompute_image/assets/part.min.css
crosscompute_image/assets/part.min.js
crosscompute_image-0.7.6.1.dist-info/DESCRIPTION.rst
crosscompute_image-0.7.6.1.dist-info/METADATA
crosscompute_image-0.7.6.1.dist-info/RECORD
crosscompute_image-0.7.6.1.dist-info/WHEEL
crosscompute_image-0.7.6.1.dist-info/entry_points.txt
crosscompute_image-0.7.6.1.dist-info/metadata.json
crosscompute_image-0.7.6.1.dist-info/top_level.txt
